crcx/__init__.py
crcx/functions.py
crcx/main.py
crcx/models.py
crcx/tables.py
crcx/utils.py
crcx/catalog/__init__.py
crcx/catalog/algorithms.py
crcx/catalog/build_algorithms.py
crcx/catalog/loaders.py
crcx/catalog/todo/__init__.py
crcx/catalog/todo/algorithms.py
crcx/catalog/todo/cfg2.py
crcx/engines/__init__.py
crcx/engines/generic.py
crcx/engines/tableized/__init__.py
crcx/engines/tableized/tables.py
CRCx-0.0.4.dist-info/LICENSE
CRCx-0.0.4.dist-info/METADATA
CRCx-0.0.4.dist-info/WHEEL
CRCx-0.0.4.dist-info/top_level.txt
CRCx-0.0.4.dist-info/RECORD
